setup.cfg
setup.py
pushkin/__init__.py
pushkin/config.py
pushkin/context.py
pushkin/pushkin_cli.py
pushkin.egg-info/PKG-INFO
pushkin.egg-info/SOURCES.txt
pushkin.egg-info/dependency_links.txt
pushkin.egg-info/entry_points.txt
pushkin.egg-info/requires.txt
pushkin.egg-info/top_level.txt
pushkin/database/__init__.py
pushkin/database/alembic.ini
pushkin/database/database.py
pushkin/database/db_cleanup.sh
pushkin/database/db_create.sh
pushkin/database/db_create.sql
pushkin/database/migrations/__init__.py
pushkin/database/migrations/env.py
pushkin/database/migrations/script.py.mako
pushkin/database/migrations/versions/50db531bbf54_database_permission.py
pushkin/database/migrations/versions/61e52d26ebea_message_blacklist.py
pushkin/database/migrations/versions/67b14b57d9e4_notification_priority.py
pushkin/database/migrations/versions/70ad8e4607cd_fix_process_user_login.py
pushkin/database/migrations/versions/822b8de2c260_merge_remove_device_id_and_message_.py
pushkin/database/migrations/versions/866d344d7b5d_ttl.py
pushkin/database/migrations/versions/8b6104b8b8c0_centralized_db.py
pushkin/database/migrations/versions/9ea5d4d49609_remove_device_id.py
pushkin/database/migrations/versions/__init__.py
pushkin/database/migrations/versions/ba3a6442af2b_merge_fix_process_user_login_and_.py
pushkin/database/migrations/versions/e2a42bcd4c02_initial_state.py
pushkin/database/model/__init__.py
pushkin/protobuf/EventMessage_pb2.py
pushkin/protobuf/PushNotificationMessage_pb2.py
pushkin/protobuf/__init__.py
pushkin/request/__init__.py
pushkin/request/event_handlers.py
pushkin/request/request_processor.py
pushkin/request/request_validators.py
pushkin/request/requests.py
pushkin/requesthandlers/__init__.py
pushkin/requesthandlers/batch.py
pushkin/requesthandlers/events.py
pushkin/requesthandlers/monitoring.py
pushkin/requesthandlers/notifications.py
pushkin/sender/__init__.py
pushkin/sender/sender_manager.py
pushkin/sender/senders.py
pushkin/sender/nordifier/__init__.py
pushkin/sender/nordifier/apns.py
pushkin/sender/nordifier/apns2_push_sender.py
pushkin/sender/nordifier/apns_push_sender.py
pushkin/sender/nordifier/constants.py
pushkin/sender/nordifier/gcm.py
