Metadata-Version: 1.1
Name: pushkin
Version: 0.1.6.1
Summary: Pushkin is a free open source tool for sending push notifications
Home-page: https://github.com/Nordeus/pushkin.git
Author: Nordeus LLC
Author-email: pushkin.dev@nordeus.com
License: MIT
Keywords: development push notifications mobile
Platform: UNKNOWN
Classifier: Development Status :: 3 - Alpha
Classifier: Intended Audience :: Developers
Classifier: Topic :: Utilities
Classifier: License :: OSI Approved :: MIT License
Classifier: Programming Language :: Python :: 2.7
